[
    {
        "name": "Isaac",
        "health": 2,
        "attack": 1,
        "item": "The D6",
        "image": "images/isaac.bmp",
        "text": "{T}: Play an additional loot card this turn.\nStarting item: The D6"
    },
    {
        "name": "Judas",
        "health": 2,
        "attack": 1,
        "item": "Book of Belial", 
        "image": "images/judas.bmp",
        "text": "{T}: Play an additional loot card this turn.\nStarting item: Book of Belial"
    },
    {
        "name": "Samson",
        "health": 2,
        "attack": 1,
        "item": "Forever Alone",
        "image": "images/samson.bmp",
        "text": "{T}: Play an additional loot card this turn.\nStarting item: Blood Lust"
    }

]